pdfsp/__init__.py
pdfsp/_dataframe.py
pdfsp/_globals.py
pdfsp/_options.py
pdfsp/_typing.py
pdfsp/_utils.py
pdfsp/cli.py
pdfsp/core.py
pdfsp-0.1.14.dist-info/METADATA
pdfsp-0.1.14.dist-info/WHEEL
pdfsp-0.1.14.dist-info/entry_points.txt
pdfsp-0.1.14.dist-info/licenses/LICENSE
pdfsp-0.1.14.dist-info/RECORD
