Metadata-Version: 2.4
Name: pdfsp
Version: 0.1.14
Summary: Extracts data from PDF files and saves it to Excel files.
Project-URL: Repository, https://github.com/SermetPekin/pdfsp
Project-URL: Documentation, https://pdfsp.readthedocs.io/en/latest/home.html
Author-email: Sermet Pekin <Sermet.Pekin@gmail.com>
License: EUPL-1.2
License-File: LICENSE
Requires-Python: >=3.10
Requires-Dist: openpyxl>=3.1.5
Requires-Dist: pandas>=2.2.3
Requires-Dist: pdfplumber>=0.11.6
Requires-Dist: requests>=2.32.3
